netgraph/__init__.py
netgraph/server.py
netgraph/aws/__init__.py
netgraph/aws/client.py
netgraph/aws/fetcher.py
netgraph/core/__init__.py
netgraph/core/exposure_detector.py
netgraph/core/graph_manager.py
netgraph/core/path_analyzer.py
netgraph/core/resource_discovery.py
netgraph/evaluators/__init__.py
netgraph/evaluators/cidr.py
netgraph/evaluators/nacl.py
netgraph/evaluators/route.py
netgraph/evaluators/security_group.py
netgraph/models/__init__.py
netgraph/models/aws_resources.py
netgraph/models/errors.py
netgraph/models/graph.py
netgraph/models/results.py
netgraph/tools/__init__.py
netgraph/utils/__init__.py
netgraph/utils/logging.py
aws_vpc_analyzer-0.5.1.dist-info/METADATA
aws_vpc_analyzer-0.5.1.dist-info/WHEEL
aws_vpc_analyzer-0.5.1.dist-info/entry_points.txt
aws_vpc_analyzer-0.5.1.dist-info/licenses/LICENSE
aws_vpc_analyzer-0.5.1.dist-info/RECORD
