Metadata-Version: 2.4
Name: aws-vpc-analyzer
Version: 0.5.1
Summary: MCP server for AWS VPC network topology analysis using NetworkX directed graphs
Project-URL: Homepage, https://github.com/ayushgoel24/mcp-netgraph
Project-URL: Documentation, https://github.com/ayushgoel24/mcp-netgraph#readme
Project-URL: Repository, https://github.com/ayushgoel24/mcp-netgraph.git
Project-URL: Issues, https://github.com/ayushgoel24/mcp-netgraph/issues
Project-URL: Changelog, https://github.com/ayushgoel24/mcp-netgraph/blob/master/CHANGELOG.md
Author: Ayush Goel
License-Expression: MIT
License-File: LICENSE
Keywords: aws,mcp,network,networkx,security,vpc
Classifier: Development Status :: 3 - Alpha
Classifier: Intended Audience :: Developers
Classifier: License :: OSI Approved :: MIT License
Classifier: Programming Language :: Python :: 3
Classifier: Programming Language :: Python :: 3.10
Classifier: Programming Language :: Python :: 3.11
Classifier: Programming Language :: Python :: 3.12
Requires-Python: >=3.10
Requires-Dist: boto3>=1.28.0
Requires-Dist: mcp>=1.0.0
Requires-Dist: networkx>=3.0
Requires-Dist: pydantic>=2.0
Provides-Extra: dev
Requires-Dist: boto3-stubs[ec2,sts]>=1.28.0; extra == 'dev'
Requires-Dist: moto>=4.0; extra == 'dev'
Requires-Dist: mypy>=1.0; extra == 'dev'
Requires-Dist: pytest-asyncio>=0.21; extra == 'dev'
Requires-Dist: pytest-cov>=4.0; extra == 'dev'
Requires-Dist: pytest>=7.0; extra == 'dev'
Requires-Dist: ruff>=0.1; extra == 'dev'
